fds/__init__.py
fds/sdk/__init__.py
fds/sdk/SecurityModeling/__init__.py
fds/sdk/SecurityModeling/api_client.py
fds/sdk/SecurityModeling/configuration.py
fds/sdk/SecurityModeling/exceptions.py
fds/sdk/SecurityModeling/model_utils.py
fds/sdk/SecurityModeling/rest.py
fds/sdk/SecurityModeling/api/__init__.py
fds/sdk/SecurityModeling/api/security_modeling_api.py
fds/sdk/SecurityModeling/apis/__init__.py
fds/sdk/SecurityModeling/model/__init__.py
fds/sdk/SecurityModeling/model/one_of_fields_fields.py
fds/sdk/SecurityModeling/model/one_of_sm_fields.py
fds/sdk/SecurityModeling/model/sm_bond_fields.py
fds/sdk/SecurityModeling/model/sm_create_parameters.py
fds/sdk/SecurityModeling/model/sm_create_parameters_root.py
fds/sdk/SecurityModeling/model/sm_create_response.py
fds/sdk/SecurityModeling/model/sm_create_response_root.py
fds/sdk/SecurityModeling/model/sm_custom_cash_flow_fields.py
fds/sdk/SecurityModeling/model/sm_delete_parameters.py
fds/sdk/SecurityModeling/model/sm_delete_parameters_root.py
fds/sdk/SecurityModeling/model/sm_delete_response.py
fds/sdk/SecurityModeling/model/sm_delete_response_root.py
fds/sdk/SecurityModeling/model/sm_error.py
fds/sdk/SecurityModeling/model/sm_fields.py
fds/sdk/SecurityModeling/model/sm_retrieve_parameters.py
fds/sdk/SecurityModeling/model/sm_retrieve_parameters_root.py
fds/sdk/SecurityModeling/model/sm_retrieve_response.py
fds/sdk/SecurityModeling/model/sm_retrieve_response_root.py
fds/sdk/SecurityModeling/model/sm_warning.py
fds/sdk/SecurityModeling/models/__init__.py
fds.sdk.SecurityModeling-0.20.16.dist-info/LICENSE
fds.sdk.SecurityModeling-0.20.16.dist-info/METADATA
fds.sdk.SecurityModeling-0.20.16.dist-info/WHEEL
fds.sdk.SecurityModeling-0.20.16.dist-info/top_level.txt
fds.sdk.SecurityModeling-0.20.16.dist-info/RECORD
